nestap_excel_create/__init__.py
nestap_excel_create/create_excel_helper.py
nestap_excel_create-1.0.2.dist-info/LICENSE.txt
nestap_excel_create-1.0.2.dist-info/METADATA
nestap_excel_create-1.0.2.dist-info/WHEEL
nestap_excel_create-1.0.2.dist-info/top_level.txt
nestap_excel_create-1.0.2.dist-info/RECORD
