Metadata-Version: 2.1
Name: nestap-excel-create
Version: 1.0.2
Summary: This package helps create excel files more efficiently and quickly
Home-page: https://github.com/alokcs17/nestap_excel
Author: Adesh Gupta and Alok Bharti
Author-email: adesh@nestap.in
License: UNKNOWN
Project-URL: Bug Tracker, https://github.com/alokcs17/nestap_excel/issues
Platform: UNKNOWN
Classifier: Programming Language :: Python :: 3
Classifier: License :: OSI Approved :: MIT License
Classifier: Operating System :: OS Independent
Requires-Python: >=3.6
License-File: LICENSE.txt
